[
	{	
		"name": "Ana Conda",
		"picture": "duck1.jpg",
		"last_message": "Hey, did you end up getting that bread?",
		"sent": "1"
	},
		{	
		"name": "Andrew Parker",
		"picture": "duck2.jpg",
		"last_message": "I have to tell you what happened at the pond",
		"sent": "3"
	},
	{	
		"name": "Erin Webb",
		"picture": "duck3.jpg",
		"last_message": "and I was like ummm quack",
		"sent": "4"
	},
	{	
		"name": "Bill Mathews",
		"picture": "duck4.jpg",
		"last_message": "I think I have webbed feet :/",
		"sent": "5"
	},
	{	
		"name": "Kim McQuack",
		"picture": "duck5.jpg",
		"last_message": "Please respond to my previous message",
		"sent": "5"
	},
	{	
		"name": "Keefer Ashton",
		"picture": "duck6.jpg",
		"last_message": "Will do now",
		"sent": "7"
	},
	{	
		"name": "Diana Timms",
		"picture": "duck7.jpg",
		"last_message": "OMG it was Bill, I saw Bill at the pond!",
		"sent": "7"
	},
	{	
		"name": "Liam Cooper",
		"picture": "duck8.jpg",
		"last_message": "Ah its just getting harder and harder these days",
		"sent": "8"
	},
	{	
		"name": "Big Ducky",
		"picture": "duck9.jpg",
		"last_message": "What did you think of the Joesph Parker fight? that last round was wild",
		"sent": "8"
	}
]